Workbook

Sheet Config
A1: THE MODEL ROOM — 3-Statement Model
A2: Step 1: pick your role. The model re-scales to fit how YOU will use it.
A4: Your role: | B4: Founder
A6: Role default — starting revenue ($):
A7: IB Analyst | B7: 4000
A8: PE Associate | B8: 8000
A9: VC Associate | B9: 6000
A10: Founder | B10: 1200
A11: Career Switcher | B11: 5000
A13: Selected starting revenue ($): | B13: =VLOOKUP(B4,A7:B11,2,FALSE)
A15: How to read this model: every formula is LIVE. Change an assumption on the Assumptions tab (amber cells) and the whole model recalculates. Cash is the residual; debt is the plug (borrow to hold minimum cash, repay the surplus).

Sheet Assumptions
A1: ASSUMPTIONS (amber = you can change)
A3: Year 0 | B3: Year 1 | C3: Year 2 | D3: Year 3 | E3: Year 4 | F3: Year 5
A4: Revenue growth % | C4: 0.2 | D4: 0.18 | E4: 0.15 | F4: 0.12 | G4: 0.1
A5: COGS % of revenue | C5: 0.6 | D5: 0.6 | E5: 0.6 | F5: 0.6 | G5: 0.6
A6: Operating expense % rev | C6: 0.15 | D6: 0.15 | E6: 0.14 | F6: 0.14 | G6: 0.13
A7: D&A % of revenue | C7: 0.04 | D7: 0.04 | E7: 0.04 | F7: 0.04 | G7: 0.04
A8: Capex % of revenue | C8: 0.06 | D8: 0.06 | E8: 0.06 | F8: 0.06 | G8: 0.06
A9: Tax rate | C9: 0.25 | D9: 0.25 | E9: 0.25 | F9: 0.25 | G9: 0.25
A10: Interest rate (debt) | C10: 0.08 | D10: 0.08 | E10: 0.08 | F10: 0.08 | G10: 0.08
A11: Days sales outstanding | C11: 45 | D11: 45 | E11: 45 | F11: 45 | G11: 45
A12: Days inventory | C12: 40 | D12: 40 | E12: 40 | F12: 40 | G12: 40
A13: Days payables | C13: 30 | D13: 30 | E13: 30 | F13: 30 | G13: 30
A14: Minimum cash % revenue | C14: 0.05 | D14: 0.05 | E14: 0.05 | F14: 0.05 | G14: 0.05
A16: OPENING BALANCES (Year 0)
A17: Opening revenue | B17: 500
A18: Opening cash | B18: 100
A19: Opening AR | B19: 50
A20: Opening inventory | B20: 40
A21: Opening AP | B21: 30
A22: Opening PP&E (net) | B22: 200
A23: Opening debt | B23: 150
A24: Opening equity | B24: 210

Sheet Income Statement
A1: INCOME STATEMENT
A3: Year 0 | B3: Year 1 | C3: Year 2 | D3: Year 3 | E3: Year 4 | F3: Year 5
A4: Revenue | B4: =Assumptions!B17*(1+Assumptions!C4) | C4: =C4*(1+Assumptions!D4) | D4: =D4*(1+Assumptions!E4) | E4: =E4*(1+Assumptions!F4) | F4: =F4*(1+Assumptions!G4)
A5: COGS | B5: =-C4*Assumptions!C5 | C5: =-D4*Assumptions!D5 | D5: =-E4*Assumptions!E5 | E5: =-F4*Assumptions!F5 | F5: =-G4*Assumptions!G5
A6: Gross profit | B6: =C4+C5 | C6: =D4+D5 | D6: =E4+E5 | E6: =F4+F5 | F6: =G4+G5
A7: Operating expense | B7: =-C5*Assumptions!C6 | C7: =-D5*Assumptions!D6 | D7: =-E5*Assumptions!E6 | E7: =-F5*Assumptions!F6 | F7: =-G5*Assumptions!G6
A8: EBITDA | B8: =C5+C7 | C8: =D5+D7 | D8: =E5+E7 | E8: =F5+F7 | F8: =G5+G7
A9: D&A | B9: =-C6*Assumptions!C7 | C9: =-D6*Assumptions!D7 | D9: =-E6*Assumptions!E7 | E9: =-F6*Assumptions!F7 | F9: =-G6*Assumptions!G7
A10: EBIT | B10: =C8+C9 | C10: =D8+D9 | D10: =E8+E9 | E10: =F8+F9 | F10: =G8+G9
A11: Interest expense | B11: =-'Balance Sheet'!C12*Assumptions!C10 | C11: =-'Balance Sheet'!C12*Assumptions!C10 | D11: =-'Balance Sheet'!D12*Assumptions!D10 | E11: =-'Balance Sheet'!E12*Assumptions!E10 | F11: =-'Balance Sheet'!F12*Assumptions!F10 | G11: =-'Balance Sheet'!G12*Assumptions!G10
A12: Pre-tax income (EBT) | B12: =C10+C11 | C12: =D10+D11 | D12: =E10+E11 | E12: =F10+F11 | F12: =G10+G11
A13: Taxes | B13: =-MAX(C12,0)*Assumptions!C9 | C13: =-MAX(D12,0)*Assumptions!D9 | D13: =-MAX(E12,0)*Assumptions!E9 | E13: =-MAX(F12,0)*Assumptions!F9 | F13: =-MAX(G12,0)*Assumptions!G9
A14: Net income | B14: =C12+C13 | C14: =D12+D13 | D14: =E12+E13 | E14: =F12+F13 | F14: =G12+G13

Sheet Balance Sheet
A1: BALANCE SHEET
A3: Year 0 | B3: Year 1 | C3: Year 2 | D3: Year 3 | E3: Year 4 | F3: Year 5
A4: Accounts receivable | B4: ='Income Statement'!G4*Assumptions!G11/365
A5: Inventory | B5: =ABS('Income Statement'!G5)*Assumptions!G12/365
A7: PP&E (net) | B7: =Assumptions!B22+'Income Statement'!C4*Assumptions!C8-'Income Statement'!C4*Assumptions!C7 | C7: =C7+'Income Statement'!D4*Assumptions!D8-'Income Statement'!D4*Assumptions!D7 | D7: =D7+'Income Statement'!E4*Assumptions!E8-'Income Statement'!E4*Assumptions!E7 | E7: =E7+'Income Statement'!F4*Assumptions!F8-'Income Statement'!F4*Assumptions!F7 | F7: =F7+'Income Statement'!G4*Assumptions!G8-'Income Statement'!G4*Assumptions!G7
A8: Subtotal (pre-cash) | B8: =SUM(C4:C7) | C8: =SUM(D4:D7) | D8: =SUM(E4:E7) | E8: =SUM(F4:F7) | F8: =SUM(G4:G7)
A9: Cash | C9: =Assumptions!B18+'Income Statement'!C14+'Income Statement'!C9-C4-Assumptions!B19-C5-Assumptions!B20+C11-Assumptions!B21+-'Income Statement'!C4*Assumptions!C8+MAX('Income Statement'!C4*Assumptions!C14-Assumptions!B18+'Income Statement'!C14+'Income Statement'!C9-C4-Assumptions!B19-C5-Assumptions!B20+C11-Assumptions!B21+-'Income Statement'!C4*Assumptions!C8,0)-MIN(MAX(Assumptions!B18+'Income Statement'!C14+'Income Statement'!C9-C4-Assumptions!B19-C5-Assumptions!B20+C11-Assumptions!B21+-'Income Statement'!C4*Assumptions!C8-'Income Statement'!C4*Assumptions!C14,0),B15) | D9: =C9+'Income Statement'!D14+'Income Statement'!D9-D4-C4-D5-C5+D11-C11+-'Income Statement'!D4*Assumptions!D8+MAX('Income Statement'!D4*Assumptions!D14-C9+'Income Statement'!D14+'Income Statement'!D9-D4-C4-D5-C5+D11-C11+-'Income Statement'!D4*Assumptions!D8,0)-MIN(MAX(C9+'Income Statement'!D14+'Income Statement'!D9-D4-C4-D5-C5+D11-C11+-'Income Statement'!D4*Assumptions!D8-'Income Statement'!D4*Assumptions!D14,0),C15) | E9: =D9+'Income Statement'!E14+'Income Statement'!E9-E4-D4-E5-D5+E11-D11+-'Income Statement'!E4*Assumptions!E8+MAX('Income Statement'!E4*Assumptions!E14-D9+'Income Statement'!E14+'Income Statement'!E9-E4-D4-E5-D5+E11-D11+-'Income Statement'!E4*Assumptions!E8,0)-MIN(MAX(D9+'Income Statement'!E14+'Income Statement'!E9-E4-D4-E5-D5+E11-D11+-'Income Statement'!E4*Assumptions!E8-'Income Statement'!E4*Assumptions!E14,0),D15) | F9: =E9+'Income Statement'!F14+'Income Statement'!F9-F4-E4-F5-E5+F11-E11+-'Income Statement'!F4*Assumptions!F8+MAX('Income Statement'!F4*Assumptions!F14-E9+'Income Statement'!F14+'Income Statement'!F9-F4-E4-F5-E5+F11-E11+-'Income Statement'!F4*Assumptions!F8,0)-MIN(MAX(E9+'Income Statement'!F14+'Income Statement'!F9-F4-E4-F5-E5+F11-E11+-'Income Statement'!F4*Assumptions!F8-'Income Statement'!F4*Assumptions!F14,0),E15) | G9: =F9+'Income Statement'!G14+'Income Statement'!G9-G4-F4-G5-F5+G11-F11+-'Income Statement'!G4*Assumptions!G8+MAX('Income Statement'!G4*Assumptions!G14-F9+'Income Statement'!G14+'Income Statement'!G9-G4-F4-G5-F5+G11-F11+-'Income Statement'!G4*Assumptions!G8,0)-MIN(MAX(F9+'Income Statement'!G14+'Income Statement'!G9-G4-F4-G5-F5+G11-F11+-'Income Statement'!G4*Assumptions!G8-'Income Statement'!G4*Assumptions!G14,0),F15)
C10: =C9+C8 | D10: =D9+D8 | E10: =E9+E8 | F10: =F9+F8 | G10: =G9+G8
A11: Accounts payable | C11: =-'Income Statement'!C5*Assumptions!C13/365 | D11: =-'Income Statement'!D5*Assumptions!D13/365 | E11: =-'Income Statement'!E5*Assumptions!E13/365 | F11: =-'Income Statement'!F5*Assumptions!F13/365 | G11: =-'Income Statement'!G5*Assumptions!G13/365
C12: =Assumptions!B23 | D12: =C15 | E12: =D15 | F12: =E15 | G12: =F15
C13: =MAX('Income Statement'!C4*Assumptions!C14-Assumptions!B18+'Income Statement'!C14+'Income Statement'!C9-C4-Assumptions!B19-C5-Assumptions!B20+C11-Assumptions!B21+-'Income Statement'!C4*Assumptions!C8,0) | D13: =MAX('Income Statement'!D4*Assumptions!D14-C9+'Income Statement'!D14+'Income Statement'!D9-D4-C4-D5-C5+D11-C11+-'Income Statement'!D4*Assumptions!D8,0) | E13: =MAX('Income Statement'!E4*Assumptions!E14-D9+'Income Statement'!E14+'Income Statement'!E9-E4-D4-E5-D5+E11-D11+-'Income Statement'!E4*Assumptions!E8,0) | F13: =MAX('Income Statement'!F4*Assumptions!F14-E9+'Income Statement'!F14+'Income Statement'!F9-F4-E4-F5-E5+F11-E11+-'Income Statement'!F4*Assumptions!F8,0) | G13: =MAX('Income Statement'!G4*Assumptions!G14-F9+'Income Statement'!G14+'Income Statement'!G9-G4-F4-G5-F5+G11-F11+-'Income Statement'!G4*Assumptions!G8,0)
C14: =MIN(MAX(Assumptions!B18+'Income Statement'!C14+'Income Statement'!C9-C4-Assumptions!B19-C5-Assumptions!B20+C11-Assumptions!B21+-'Income Statement'!C4*Assumptions!C8-'Income Statement'!C4*Assumptions!C14,0),B15) | D14: =MIN(MAX(C9+'Income Statement'!D14+'Income Statement'!D9-D4-C4-D5-C5+D11-C11+-'Income Statement'!D4*Assumptions!D8-'Income Statement'!D4*Assumptions!D14,0),C15) | E14: =MIN(MAX(D9+'Income Statement'!E14+'Income Statement'!E9-E4-D4-E5-D5+E11-D11+-'Income Statement'!E4*Assumptions!E8-'Income Statement'!E4*Assumptions!E14,0),D15) | F14: =MIN(MAX(E9+'Income Statement'!F14+'Income Statement'!F9-F4-E4-F5-E5+F11-E11+-'Income Statement'!F4*Assumptions!F8-'Income Statement'!F4*Assumptions!F14,0),E15) | G14: =MIN(MAX(F9+'Income Statement'!G14+'Income Statement'!G9-G4-F4-G5-F5+G11-F11+-'Income Statement'!G4*Assumptions!G8-'Income Statement'!G4*Assumptions!G14,0),F15)
C15: =C12+C13-C14 | D15: =D12+D13-D14 | E15: =E12+E13-E14 | F15: =F12+F13-F14 | G15: =G12+G13-G14
A16: Equity (retained) | C16: =Assumptions!B24+'Income Statement'!C14 | D16: =C16+'Income Statement'!D14 | E16: =D16+'Income Statement'!E14 | F16: =E16+'Income Statement'!F14 | G16: =F16+'Income Statement'!G14
C17: =C11+C15+C16 | D17: =D11+D15+D16 | E17: =E11+E15+E16 | F17: =F11+F15+F16 | G17: =G11+G15+G16
A18: Balance check (must = 0) | C18: =C10-C17 | D18: =D10-D17 | E18: =E10-E17 | F18: =F10-F17 | G18: =G10-G17

Sheet Cash Flow
A1: CASH FLOW STATEMENT
A3: Year 0 | B3: Year 1 | C3: Year 2 | D3: Year 3 | E3: Year 4 | F3: Year 5
A4: Net income | B4: ='Income Statement'!C14 | C4: ='Income Statement'!D14 | D4: ='Income Statement'!E14 | E4: ='Income Statement'!F14 | F4: ='Income Statement'!G14
A5: D&A | B5: ='Income Statement'!C9 | C5: ='Income Statement'!D9 | D5: ='Income Statement'!E9 | E5: ='Income Statement'!F9 | F5: ='Income Statement'!G9
A6: Δ Accounts receivable | B6: =-('Balance Sheet'!C4-'Balance Sheet'!B4) | C6: =-('Balance Sheet'!D4-'Balance Sheet'!C4) | D6: =-('Balance Sheet'!E4-'Balance Sheet'!D4) | E6: =-('Balance Sheet'!F4-'Balance Sheet'!E4) | F6: =-('Balance Sheet'!G4-'Balance Sheet'!F4)
A7: Δ Inventory | B7: =-('Balance Sheet'!C5-'Balance Sheet'!B5) | C7: =-('Balance Sheet'!D5-'Balance Sheet'!C5) | D7: =-('Balance Sheet'!E5-'Balance Sheet'!D5) | E7: =-('Balance Sheet'!F5-'Balance Sheet'!E5) | F7: =-('Balance Sheet'!G5-'Balance Sheet'!F5)
A8: Δ Accounts payable | B8: ='Balance Sheet'!C11-'Balance Sheet'!B11 | C8: ='Balance Sheet'!D11-'Balance Sheet'!C11 | D8: ='Balance Sheet'!E11-'Balance Sheet'!D11 | E8: ='Balance Sheet'!F11-'Balance Sheet'!E11 | F8: ='Balance Sheet'!G11-'Balance Sheet'!F11
A9: Cash from operations | B9: =SUM(C4:C8) | C9: =SUM(D4:D8) | D9: =SUM(E4:E8) | E9: =SUM(F4:F8) | F9: =SUM(G4:G8)
A10: Capex | B10: =-'Income Statement'!C4*Assumptions!C8 | C10: =-'Income Statement'!D4*Assumptions!D8 | D10: =-'Income Statement'!E4*Assumptions!E8 | E10: =-'Income Statement'!F4*Assumptions!F8 | F10: =-'Income Statement'!G4*Assumptions!G8
A11: Cash from investing | B11: =C10 | C11: =D10 | D11: =E10 | E11: =F10 | F11: =G10
A12: Debt draw | B12: ='Balance Sheet'!C13 | C12: ='Balance Sheet'!D13 | D12: ='Balance Sheet'!E13 | E12: ='Balance Sheet'!F13 | F12: ='Balance Sheet'!G13
A13: Debt repay | B13: =-'Balance Sheet'!C14 | C13: =-'Balance Sheet'!D14 | D13: =-'Balance Sheet'!E14 | E13: =-'Balance Sheet'!F14 | F13: =-'Balance Sheet'!G14
A14: Cash from financing | B14: =SUM(C12:C13) | C14: =SUM(D12:D13) | D14: =SUM(E12:E13) | E14: =SUM(F12:F13) | F14: =SUM(G12:G13)
A15: Net change in cash | B15: =C10+C12+C14 | C15: =D10+D12+D14 | D15: =E10+E12+E14 | E15: =F10+F12+F14 | F15: =G10+G12+G14
A16: Beginning cash | B16: =Assumptions!B18 | C16: ='Balance Sheet'!C9 | D16: ='Balance Sheet'!D9 | E16: ='Balance Sheet'!E9 | F16: ='Balance Sheet'!F9
A17: Ending cash | B17: =C15+C16 | C17: =D15+D16 | D17: =E15+E16 | E17: =F15+F16 | F17: =G15+G16

Sheet README
A1: THE MODEL ROOM — 3-Statement Model
A3: What you have: a fully-linked, minimum-cash 3-statement model.
A4: Every cell is a LIVE formula. Change amber assumptions and the model recalculates.
A6: Tabs:
A7: • Config — pick your role; the model re-scales to fit how YOU use it.
A8: • Assumptions — the only inputs you normally touch (amber cells).
A9: • Income Statement / Balance Sheet / Cash Flow — all linked.
A10: • Balance check (BS last row) MUST equal 0. It does, by construction.
A12: The differentiator: most free templates don't balance and break under scrutiny.
A13: This one does — and it's built to the conventions bulge-bracket banks use,
A14: so you can defend every number in an interview or in front of a partner.
A16: How to present it: open Config, set your role, then walk a reviewer through
... A18: debt is the plug. That narrative is what gets you the offer / the check.
